mcp_server_qdrant/__init__.py
mcp_server_qdrant/main.py
mcp_server_qdrant/mcp_server.py
mcp_server_qdrant/qdrant.py
mcp_server_qdrant/server.py
mcp_server_qdrant/settings.py
mcp_server_qdrant/common/__init__.py
mcp_server_qdrant/common/filters.py
mcp_server_qdrant/common/func_tools.py
mcp_server_qdrant/common/wrap_filters.py
mcp_server_qdrant/embeddings/__init__.py
mcp_server_qdrant/embeddings/base.py
mcp_server_qdrant/embeddings/factory.py
mcp_server_qdrant/embeddings/fastembed.py
mcp_server_qdrant/embeddings/types.py
qdrant_llamaindex_mcp_server-0.1.2.dist-info/METADATA
qdrant_llamaindex_mcp_server-0.1.2.dist-info/WHEEL
qdrant_llamaindex_mcp_server-0.1.2.dist-info/entry_points.txt
qdrant_llamaindex_mcp_server-0.1.2.dist-info/licenses/LICENSE
qdrant_llamaindex_mcp_server-0.1.2.dist-info/RECORD
