Metadata-Version: 2.4
Name: qdrant-llamaindex-mcp-server
Version: 0.1.2
Summary: MCP server for reading LlamaIndex documents stored in Qdrant vector database
Project-URL: Homepage, https://github.com/azhang/qdrant-llamaindex-mcp-server
Project-URL: Repository, https://github.com/azhang/qdrant-llamaindex-mcp-server
Project-URL: Issues, https://github.com/azhang/qdrant-llamaindex-mcp-server/issues
Author: Allie
License-Expression: Apache-2.0
License-File: LICENSE
Keywords: embeddings,llamaindex,mcp,qdrant,vector-database
Classifier: Development Status :: 4 - Beta
Classifier: Intended Audience :: Developers
Classifier: License :: OSI Approved :: Apache Software License
Classifier: Programming Language :: Python :: 3
Classifier: Programming Language :: Python :: 3.10
Classifier: Programming Language :: Python :: 3.11
Classifier: Programming Language :: Python :: 3.12
Classifier: Topic :: Database :: Database Engines/Servers
Classifier: Topic :: Software Development :: Libraries :: Python Modules
Requires-Python: >=3.10
Requires-Dist: fastembed>=0.6.0
Requires-Dist: fastmcp>=2.7.0
Requires-Dist: pydantic>=2.10.6
Requires-Dist: qdrant-client>=1.12.0
